dmtools/__init__.py
dmtools/_log.py
dmtools/adjustments.py
dmtools/animation.py
dmtools/arrange.py
dmtools/colorspace.py
dmtools/io.py
dmtools/sound.py
dmtools/transform.py
dmtools/resources/__init__.py
dmtools/resources/ascii.pgm
dmtools/tests/__init__.py
dmtools/tests/test_adjustments.py
dmtools/tests/test_arrange.py
dmtools/tests/test_colorspace.py
dmtools/tests/test_io.py
dmtools/tests/test_transform.py
dmtools-0.5.0.dist-info/LICENSE.md
dmtools-0.5.0.dist-info/METADATA
dmtools-0.5.0.dist-info/WHEEL
dmtools-0.5.0.dist-info/top_level.txt
dmtools-0.5.0.dist-info/RECORD
