Metadata-Version: 2.1
Name: dmtools
Version: 0.5.0
Summary: A Python package providing low-level tools for working with digital media programmatically.
Home-page: https://github.com/henryrobbins/dmtools.git
Author: Henry Robbins
Author-email: hwr26@cornell.edu
License: UNKNOWN
Platform: UNKNOWN
Classifier: Programming Language :: Python :: 3.5
Classifier: Programming Language :: Python :: 3.6
Classifier: Programming Language :: Python :: 3.7
Classifier: Programming Language :: Python :: 3.8
Classifier: License :: OSI Approved :: MIT License
Classifier: Operating System :: OS Independent
Requires-Python: >=3.5
License-File: LICENSE.md
Requires-Dist: numpy (>=1.19)
Requires-Dist: imageio (>=2.9)
Requires-Dist: imageio-ffmpeg (>=0.4.5)
Requires-Dist: scipy (>=1.6)
Requires-Dist: typing (>=3.7)
Provides-Extra: dev
Requires-Dist: pytest (>=5) ; extra == 'dev'
Requires-Dist: mock (>=3) ; extra == 'dev'
Requires-Dist: coverage (>=4.5) ; extra == 'dev'
Requires-Dist: tox (>=3) ; extra == 'dev'
